rx/__init__.py
rx/__version__.py
rx/analyzer.py
rx/compressed_index.py
rx/compression.py
rx/favicon.svg
rx/file_utils.py
rx/frontend_manager.py
rx/hooks.py
rx/indexer.py
rx/models.py
rx/path_security.py
rx/prometheus.py
rx/regex.py
rx/request_store.py
rx/rg_json.py
rx/scheduler.py
rx/seekable_index.py
rx/seekable_zstd.py
rx/task_manager.py
rx/trace.py
rx/trace_cache.py
rx/unified_index.py
rx/utils.py
rx/web.py
rx/analyze/__init__.py
rx/analyze/helpers.py
rx/analyze/prefix_pattern.py
rx/analyze/prescan.py
rx/analyze/detectors/__init__.py
rx/analyze/detectors/base.py
rx/analyze/detectors/error_keyword.py
rx/analyze/detectors/format_deviation.py
rx/analyze/detectors/high_entropy.py
rx/analyze/detectors/indentation.py
rx/analyze/detectors/json_dump.py
rx/analyze/detectors/line_length.py
rx/analyze/detectors/prefix_deviation.py
rx/analyze/detectors/timestamp_gap.py
rx/analyze/detectors/traceback.py
rx/analyze/detectors/warning_keyword.py
rx/cli/__init__.py
rx/cli/check.py
rx/cli/compress.py
rx/cli/index.py
rx/cli/main.py
rx/cli/prometheus.py
rx/cli/samples.py
rx/cli/serve.py
rx/cli/trace.py
rx_tool-2.2.1.dist-info/METADATA
rx_tool-2.2.1.dist-info/WHEEL
rx_tool-2.2.1.dist-info/entry_points.txt
rx_tool-2.2.1.dist-info/RECORD
