Metadata-Version: 2.4
Name: rx-tool
Version: 2.2.1
Summary: High-performance file search and analysis tool powered by ripgrep
Project-URL: Homepage, https://github.com/wlame/rx-tool
Project-URL: Repository, https://github.com/wlame/rx-tool
Project-URL: Issues, https://github.com/wlame/rx-tool/issues
Project-URL: Changelog, https://github.com/wlame/rx-tool/blob/main/CHANGELOG.md
Author-email: wlame <wlarne@gmail.com>
License: MIT
Keywords: cli,file-search,log-analysis,pattern-matching,regex,ripgrep,search,tool
Classifier: Development Status :: 4 - Beta
Classifier: Environment :: Console
Classifier: Intended Audience :: Developers
Classifier: Intended Audience :: System Administrators
Classifier: License :: OSI Approved :: MIT License
Classifier: Programming Language :: Python :: 3
Classifier: Programming Language :: Python :: 3.13
Classifier: Topic :: Text Processing
Classifier: Topic :: Utilities
Requires-Python: >=3.13
Requires-Dist: click>=8.1.0
Requires-Dist: drain3>=0.9.11
Requires-Dist: fastapi>=0.118.0
Requires-Dist: httpx>=0.28.1
Requires-Dist: prometheus-client>=0.21.0
Requires-Dist: psutil>=7.1.2
Requires-Dist: pytest>=8.4.2
Requires-Dist: sh>=2.2.2
Requires-Dist: uvicorn>=0.37.0
Requires-Dist: zstandard>=0.23.0
